Metadata-Version: 1.0
Name: lemonbar-manager
Version: 1.0.1
Summary: A management framework for Lemonbar
Home-page: https://github.com/vimist/lemonbar-manager
Author: Vimist
Author-email: UNKNOWN
License: UNKNOWN
Platform: UNKNOWN
